lazymap/__init__.py
lazymap/py.typed
lazymap-1.0.1.dist-info/LICENSE
lazymap-1.0.1.dist-info/METADATA
lazymap-1.0.1.dist-info/WHEEL
lazymap-1.0.1.dist-info/RECORD
