Metadata-Version: 2.1
Name: lazymap
Version: 1.0.1
Summary: A lazy mapping whose values are evaluated when accessed
Home-page: https://github.com/abrahammurciano/python-lazymap
License: GPLv3
Author: Abraham Murciano
Author-email: abrahammurciano@gmail.com
Requires-Python: >=3.8
Classifier: License :: Other/Proprietary License
Classifier: Programming Language :: Python :: 3
Classifier: Programming Language :: Python :: 3.8
Classifier: Programming Language :: Python :: 3.9
Classifier: Programming Language :: Python :: 3.10
Classifier: Programming Language :: Python :: 3.11
Classifier: Programming Language :: Python :: 3.12
Requires-Dist: typing-extensions (>=4.11.0)
Project-URL: Documentation, https://abrahammurciano.github.io/python-lazymap/lazymap
Project-URL: Repository, https://github.com/abrahammurciano/python-lazymap
